universal_name_format/__init__.py
universal_name_format/models/__init__.py
universal_name_format/models/name.py
universal_name_format/models/orders.py
universal_name_format/utils/__init__.py
universal_name_format/utils/converter.py
universal_name_format-0.1.4.dist-info/AUTHORS
universal_name_format-0.1.4.dist-info/LICENSE
universal_name_format-0.1.4.dist-info/METADATA
universal_name_format-0.1.4.dist-info/WHEEL
universal_name_format-0.1.4.dist-info/top_level.txt
universal_name_format-0.1.4.dist-info/RECORD
